reclaim_python_sdk/__init__.py
reclaim_python_sdk/reclaim.py
reclaim_python_sdk/smart_contract.py
reclaim_python_sdk/witness.py
reclaim_python_sdk/contract_data/__init__.py
reclaim_python_sdk/contract_data/abi.py
reclaim_python_sdk/utils/__init__.py
reclaim_python_sdk/utils/constants.py
reclaim_python_sdk/utils/errors.py
reclaim_python_sdk/utils/interfaces.py
reclaim_python_sdk/utils/logger.py
reclaim_python_sdk/utils/proof_utils.py
reclaim_python_sdk/utils/session_utils.py
reclaim_python_sdk/utils/types.py
reclaim_python_sdk/utils/validation_utils.py
reclaim_python_sdk/utils/validators.py
reclaim_python_sdk-1.0.2.dist-info/LICENSE
reclaim_python_sdk-1.0.2.dist-info/METADATA
reclaim_python_sdk-1.0.2.dist-info/WHEEL
reclaim_python_sdk-1.0.2.dist-info/top_level.txt
reclaim_python_sdk-1.0.2.dist-info/RECORD
