Metadata-Version: 2.1
Name: reclaim_python_sdk
Version: 1.0.2
Summary: Python SDK for the Reclaim Protocol
Home-page: https://github.com/reclaimprotocol/reclaim-python-sdk
Author: Reclaim Protocol
Author-email: engineering@creatoros.co
Classifier: Programming Language :: Python :: 3
Classifier: License :: OSI Approved :: MIT License
Classifier: Operating System :: OS Independent
Requires-Python: >=3.7
License-File: LICENSE
Requires-Dist: web3>=6.0.0
Requires-Dist: canonicaljson>=1.0.0
Requires-Dist: eth-account>=0.8.0
Requires-Dist: typing-extensions>=4.5.0
Requires-Dist: aiohttp>=3.8.0
Requires-Dist: python-dotenv>=1.0.0
Requires-Dist: requests>=2.32.3
Requires-Dist: httpx>=0.24.0
Requires-Dist: asyncio>=3.4.3
Requires-Dist: safe-pysha3>=1.0.2
Requires-Dist: json-canonical>=2.0.0
